{
  "formatVersion": 1,
  "database": {
    "version": 1,
    "identityHash": "c6e0818f071421224282fe3500e5eac7",
    "entities": [
      {
        "tableName": "currencies",
        "createSql": "CREATE TABLE IF NOT EXISTS `${TABLE_NAME}` (`uid` INTEGER NOT NULL, `currency_name` TEXT, `currency_rate` REAL NOT NULL, `currency_icon` INTEGER NOT NULL, `currency_code` TEXT, PRIMARY KEY(`uid`))",
        "fields": [
          {
            "fieldPath": "uid",
            "columnName": "uid",
            "affinity": "INTEGER",
            "notNull": true
          },
          {
            "fieldPath": "description",
            "columnName": "currency_name",
            "affinity": "TEXT",
            "notNull": false
          },
          {
            "fieldPath": "value",
            "columnName": "currency_rate",
            "affinity": "REAL",
            "notNull": true
          },
          {
            "fieldPath": "icon",
            "columnName": "currency_icon",
            "affinity": "INTEGER",
            "notNull": true
          },
          {
            "fieldPath": "code",
            "columnName": "currency_code",
            "affinity": "TEXT",
            "notNull": false
          }
        ],
        "primaryKey": {
          "columnNames": [
            "uid"
          ],
          "autoGenerate": false
        },
        "indices": [],
        "foreignKeys": []
      }
    ],
    "views": [],
    "setupQueries": [
      "CREATE TABLE IF NOT EXISTS room_master_table (id INTEGER PRIMARY KEY,identity_hash TEXT)",
      "INSERT OR REPLACE INTO room_master_table (id,identity_hash) VALUES(42, 'c6e0818f071421224282fe3500e5eac7')"
    ]
  }
}